CHANGES.txt
LICENSE.txt
README.txt
buildout.cfg
setup.py
src/getpaid/__init__.py
src/getpaid.core.egg-info/PKG-INFO
src/getpaid.core.egg-info/SOURCES.txt
src/getpaid.core.egg-info/dependency_links.txt
src/getpaid.core.egg-info/namespace_packages.txt
src/getpaid.core.egg-info/not-zip-safe
src/getpaid.core.egg-info/requires.txt
src/getpaid.core.egg-info/top_level.txt
src/getpaid/core/__init__.py
src/getpaid/core/cart.py
src/getpaid/core/configure.zcml
src/getpaid/core/event.py
src/getpaid/core/fields.py
src/getpaid/core/i18n.sh
src/getpaid/core/interfaces.py
src/getpaid/core/item.py
src/getpaid/core/options.py
src/getpaid/core/options.txt
src/getpaid/core/order.py
src/getpaid/core/order.txt
src/getpaid/core/payment.py
src/getpaid/core/recurrent.txt
src/getpaid/core/reports.py
src/getpaid/core/router.py
src/getpaid/core/shipping.py
src/getpaid/core/store.py
src/getpaid/core/tax.py
src/getpaid/core/vocabularies.py
src/getpaid/core/locales/empty.pt
src/getpaid/core/locales/getpaid.pot
src/getpaid/core/locales/manual.pot
src/getpaid/core/locales/da/LC_MESSAGES/getpaid.mo
src/getpaid/core/locales/da/LC_MESSAGES/getpaid.po
src/getpaid/core/locales/de/LC_MESSAGES/getpaid.mo
src/getpaid/core/locales/de/LC_MESSAGES/getpaid.po
src/getpaid/core/locales/en/LC_MESSAGES/getpaid.mo
src/getpaid/core/locales/en/LC_MESSAGES/getpaid.po
src/getpaid/core/locales/es/LC_MESSAGES/getpaid.mo
src/getpaid/core/locales/es/LC_MESSAGES/getpaid.po
src/getpaid/core/locales/fi/LC_MESSAGES/getpaid.mo
src/getpaid/core/locales/fi/LC_MESSAGES/getpaid.po
src/getpaid/core/locales/fr/LC_MESSAGES/getpaid.mo
src/getpaid/core/locales/fr/LC_MESSAGES/getpaid.po
src/getpaid/core/locales/hu/LC_MESSAGES/getpaid.mo
src/getpaid/core/locales/hu/LC_MESSAGES/getpaid.po
src/getpaid/core/locales/it/LC_MESSAGES/getpaid.mo
src/getpaid/core/locales/it/LC_MESSAGES/getpaid.po
src/getpaid/core/locales/ja/LC_MESSAGES/getpaid.mo
src/getpaid/core/locales/ja/LC_MESSAGES/getpaid.po
src/getpaid/core/locales/nl/LC_MESSAGES/getpaid.mo
src/getpaid/core/locales/nl/LC_MESSAGES/getpaid.po
src/getpaid/core/locales/pt/LC_MESSAGES/getpaid.mo
src/getpaid/core/locales/pt/LC_MESSAGES/getpaid.po
src/getpaid/core/locales/pt_BR/LC_MESSAGES/getpaid.mo
src/getpaid/core/locales/pt_BR/LC_MESSAGES/getpaid.po
